mobius_client-1.0.2.dist-info/LICENSE.txt
mobius_client-1.0.2.dist-info/METADATA
mobius_client-1.0.2.dist-info/RECORD
mobius_client-1.0.2.dist-info/WHEEL
mobius_client-1.0.2.dist-info/top_level.txt
mobius_client_python/__init__.py
mobius_client_python/client.py
mobius_client_python/app/__init__.py
mobius_client_python/app/app.py
mobius_client_python/app/app_builder.py
mobius_client_python/auth/__init__.py
mobius_client_python/auth/challenge.py
mobius_client_python/auth/jwt.py
mobius_client_python/auth/sign.py
mobius_client_python/auth/token.py
mobius_client_python/blockchain/__init__.py
mobius_client_python/blockchain/account.py
mobius_client_python/blockchain/account_builder.py
mobius_client_python/blockchain/add_cosigner.py
mobius_client_python/blockchain/create_trustline.py
mobius_client_python/blockchain/friend_bot.py
mobius_client_python/utils/__init__.py
mobius_client_python/utils/keypair.py
