Metadata-Version: 2.1
Name: mobius-client
Version: 1.0.2
Summary: Mobius DApp Store SDK
Home-page: https://github.com/mobius-network/mobius-client-python
Author: Mobius Team
Author-email: developers@mobius.network
License: UNKNOWN
Project-URL: Mobius Store, https://store.mobius.network
Project-URL: Documentation, https://docs.mobius.network
Project-URL: Bug Reports, https://github.com/mobius-network/mobius-client-python/issues
Project-URL: Source, https://github.com/mobius-network/mobius-client-python/
Platform: UNKNOWN
Classifier: Development Status :: 4 - Beta
Classifier: Intended Audience :: Developers
Classifier: Intended Audience :: Financial and Insurance Industry
Classifier: License :: OSI Approved :: MIT License
Classifier: Operating System :: OS Independent
Classifier: Programming Language :: Python
Classifier: Programming Language :: Python :: 3
Classifier: Topic :: Software Development :: Libraries :: Python Modules
Provides-Extra: example
Requires-Dist: PyJWT
Requires-Dist: stellar-base
Provides-Extra: example
Requires-Dist: flask; extra == 'example'
